Workbook
Name _Hlk157767716: Sheet1!$A$4
Name Clientes: #REF!

Sheet Sheet1
A1: =COUNTA(B20:B70)+1 -> 18
B2: DADOS DE FATURAMENTO
B3: Razão Social: | C3: =Cliente!A2 -> SINTESE BIOTECNOLOGIA LTDA
B4: CNPJ/CPF: | C4: =Cliente!B2 -> 13.545.241/0001-68 | D4: Insc. Estadual | E4: =Cliente!C2 -> 0017632680098 | F4: ORDEM DE COMPRA
B5: Endereço: | C5: =Cliente!D2 -> Avenida Del Rey, 111, Belo Horizonte - 30775-240 (MG) | F5: OC 772
B6: Contato: | C6: Nome: Enzo Ferraz|Email: enzo@sintesebio.com.br | D6: CEP: | E6: =Cliente!E2 -> 30775-240
B9: DADOS PARA ENTREGA
B10: Razão Social | C10: =Cliente!A2 -> SINTESE BIOTECNOLOGIA LTDA | F10: DATA DE EMISSÃO
B11: End Entrega | C11: =Cliente!F2 -> Avenida Del Rey, 111, Belo Horizonte - 30775-240 (MG) | F11: =TODAY() -> 46076 | J11: =DAY(F11) -> 23
B12: CNPJ/CPF: | C12: 04.562.591/0001-41 | D12: CEP: | E12: =Cliente!G2 -> 30775-240
B15: Fornecedor | C15: BIO-RAD LABORATORIOS BRASIL LTDA
B16: CNPJ/CPF: | C16: 03.188.198/0006-81 | D16: Insc. Estadual | E16: 004714566.01-13
B17: Endereço: | C17: Estrada Municipal Luiz Lopes Neto, 756 - Complemento GALPAO300 PARTE C - Distrito Industrial Tenentes, Extrema - MG, CEP 37645-050
B19: Material | C19: Descrição | D19: Quantidade | E19: Valor Unitário | F19: Valor R$ | G19: Data Entrega
B20: 1704446 | C20: =IFERROR(VLOOKUP(B20,Preço!B:C,2,0),"") -> PENTE MOD SUB CELLDE ALTURA FIXA 15 POCOS,1.5MM | D20: 2 | E20: =IFERROR(VLOOKUP(B20,Preço!B:D,3,0),"") -> 158.94 | F20: =IFERROR(SUM(E20*D20),"") -> 317.88 | G20: =IF(D20="","",$F$11+8) -> 46084
B21: 1610375 | C21: =IFERROR(VLOOKUP(B21,Preço!B:C,2,0),"") -> Padr?o de peso molecular Kaleidoscope (10-250 kD), 500 ?l, 50 aplicac?es | D21: 1 | E21: =IFERROR(VLOOKUP(B21,Preço!B:D,3,0),"") -> 492.24 | F21: =IFERROR(SUM(E21*D21),"") -> 492.24 | G21: =IF(D21="","",$F$11+8) -> 46084
B22: 1704448 | C22: =IFERROR(VLOOKUP(B22,Preço!B:C,2,0),"") -> PENTE FIXO PARA SISTEMA SUB-CELL E WIDE MINI-SUB CELL 1,5MM | D22: 2 | E22: =IFERROR(VLOOKUP(B22,Preço!B:D,3,0),"") -> 200.55 | F22: =IFERROR(SUM(E22*D22),"") -> 401.1 | G22: =IF(D22="","",$F$11+8) -> 46084
B23: 1704416 | C23: =IFERROR(VLOOKUP(B23,Preço!B:C,2,0),"") -> BANDEJA UV, MOD SUB CELL 15X10CM | D23: 1 | E23: =IFERROR(VLOOKUP(B23,Preço!B:D,3,0),"") -> 696.52 | F23: =IFERROR(SUM(E23*D23),"") -> 696.52 | G23: =IF(D23="","",$F$11+8) -> 46084
B24: 1658001 | C24: =IFERROR(VLOOKUP(B24,Preço!B:C,2,0),"") -> MINI PROTEAN TETRA CELL 10WELL | D24: 1 | E24: =IFERROR(VLOOKUP(B24,Preço!B:D,3,0),"") -> 5939.79 | F24: =IFERROR(SUM(E24*D24),"") -> 5939.79 | G24: =IF(D24="","",$F$11+8) -> 46084
B25: 1704422 | C25: =IFERROR(VLOOKUP(B25,Preço!B:C,2,0),"") -> SUPORTE PARA MONTAGEM DE GEIS, MODELO MINI GEL CASTER | D25: 2 | E25: =IFERROR(VLOOKUP(B25,Preço!B:D,3,0),"") -> 675.72 | F25: =IFERROR(SUM(E25*D25),"") -> 1351.44 | G25: =IF(D25="","",$F$11+8) -> 46084
B26: 5000113 | C26: =IFERROR(VLOOKUP(B26,Preço!B:C,2,0),"") -> REAGENTE A, DC PROTEIN ASSAY REAGENT, 250ML | D26: 1 | E26: =IFERROR(VLOOKUP(B26,Preço!B:D,3,0),"") -> 460.12 | F26: =IFERROR(SUM(E26*D26),"") -> 460.12 | G26: =IF(D26="","",$F$11+8) -> 46084
B27: 1704381 | C27: =IFERROR(VLOOKUP(B27,Preço!B:C,2,0),"") -> CUBA DE ELETROFOSE HORIZONTAL | D27: 1 | E27: =IFERROR(VLOOKUP(B27,Preço!B:D,3,0),"") -> 1691.78 | F27: =IFERROR(SUM(E27*D27),"") -> 1691.78 | G27: =IF(D27="","",$F$11+8) -> 46084
B28: 1725130 | C28: =IFERROR(VLOOKUP(B28,Preço!B:C,2,0),"") -> ITAQ SUPERMIX UNIVERSAL DE SONDAS | D28: 1 | E28: =IFERROR(VLOOKUP(B28,Preço!B:D,3,0),"") -> 921.93 | F28: =IFERROR(SUM(E28*D28),"") -> 921.93 | G28: =IF(D28="","",$F$11+8) -> 46084
B29: 1725131 | C29: =IFERROR(VLOOKUP(B29,Preço!B:C,2,0),"") -> ITAQ SUPERMIX SONDA, 500 X 20UL DE REACAO, 5ML | D29: 5 | E29: =IFERROR(VLOOKUP(B29,Preço!B:D,3,0),"") -> 1281.94 | F29: =IFERROR(SUM(E29*D29),"") -> 6409.7 | G29: =IF(D29="","",$F$11+8) -> 46084
B30: 1704425 | C30: =IFERROR(VLOOKUP(B30,Preço!B:C,2,0),"") -> TRAVAS LATERAIS PARA MONTAGEM DE GEIS, WIDE MINI CELL GT | D30: 1 | E30: =IFERROR(VLOOKUP(B30,Preço!B:D,3,0),"") -> 530.92 | F30: =IFERROR(SUM(E30*D30),"") -> 530.92 | G30: =IF(D30="","",$F$11+8) -> 46084
B31: 1704426 | C31: =IFERROR(VLOOKUP(B31,Preço!B:C,2,0),"") -> BANDEJA UV , MOD SUB CELL, 15X7CM | D31: 1 | E31: =IFERROR(VLOOKUP(B31,Preço!B:D,3,0),"") -> 656.58 | F31: =IFERROR(SUM(E31*D31),"") -> 656.58 | G31: =IF(D31="","",$F$11+8) -> 46084
... B35: 1725201 | C35: =IFERROR(VLOOKUP(B35,Preço!B:C,2,0),"") -> MIX PARA REACOES EVAGREEN 500X20UL | D35: 5 | E35: =IFERROR(VLOOKUP(B35,Preço!B:D,3,0),"") -> 1934.94 | F35: =IFERROR(SUM(E35*D35),"") -> 9674.7 | G35: =IF(D35="","",$F$11+8) -> 46084
B36: 1610154 | C36: =IFERROR(VLOOKUP(B36,Preço!B:C,2,0),"") -> 30% SOLUCAO ACRIL/BIS 19:1,,500ML | E36: =IFERROR(VLOOKUP(B36,Preço!B:D,3,0),"") -> 444.86 | F36: =IFERROR(SUM(E36*D36),"") -> 0 | G36: =IF(D36="","",$F$11+8)
C37: =IFERROR(VLOOKUP(B37,Preço!B:C,2,0),"") | E37: =IFERROR(VLOOKUP(B37,Preço!B:D,3,0),"") | F37: =IFERROR(SUM(E37*D37),"") | G37: =IF(D37="","",$F$11+8)
C38: =IFERROR(VLOOKUP(B38,Preço!B:C,2,0),"") | E38: =IFERROR(VLOOKUP(B38,Preço!B:D,3,0),"") | F38: =IFERROR(SUM(E38*D38),"") | G38: =IF(D38="","",$F$11+8)
C39: =IFERROR(VLOOKUP(B39,Preço!B:C,2,0),"") | E39: =IFERROR(VLOOKUP(B39,Preço!B:D,3,0),"") | F39: =IFERROR(SUM(E39*D39),"") | G39: =IF(D39="","",$F$11+8)
C40: =IFERROR(VLOOKUP(B40,Preço!B:C,2,0),"") | E40: =IFERROR(VLOOKUP(B40,Preço!B:D,3,0),"") | F40: =IFERROR(SUM(E40*D40),"") | G40: =IF(D40="","",$F$11+8)
C41: =IFERROR(VLOOKUP(B41,Preço!B:C,2,0),"") | E41: =IFERROR(VLOOKUP(B41,Preço!B:D,3,0),"") | F41: =IFERROR(SUM(E41*D41),"") | G41: =IF(D41="","",$F$11+8)
C42: =IFERROR(VLOOKUP(B42,Preço!B:C,2,0),"") | E42: =IFERROR(VLOOKUP(B42,Preço!B:D,3,0),"") | F42: =IFERROR(SUM(E42*D42),"") | G42: =IF(D42="","",$F$11+8)
C43: =IFERROR(VLOOKUP(B43,Preço!B:C,2,0),"") | E43: =IFERROR(VLOOKUP(B43,Preço!B:D,3,0),"") | F43: =IFERROR(SUM(E43*D43),"") | G43: =IF(D43="","",$F$11+8)
C44: =IFERROR(VLOOKUP(B44,Preço!B:C,2,0),"") | E44: =IFERROR(VLOOKUP(B44,Preço!B:D,3,0),"") | F44: =IFERROR(SUM(E44*D44),"") | G44: =IF(D44="","",$F$11+8)
C45: =IFERROR(VLOOKUP(B45,Preço!B:C,2,0),"") | E45: =IFERROR(VLOOKUP(B45,Preço!B:D,3,0),"") | F45: =IFERROR(SUM(E45*D45),"") | G45: =IF(D45="","",$F$11+8)
C46: =IFERROR(VLOOKUP(B46,Preço!B:C,2,0),"") | E46: =IFERROR(VLOOKUP(B46,Preço!B:D,3,0),"") | F46: =IFERROR(SUM(E46*D46),"") | G46: =IF(D46="","",$F$11+8)
C47: =IFERROR(VLOOKUP(B47,Preço!B:C,2,0),"") | E47: =IFERROR(VLOOKUP(B47,Preço!B:D,3,0),"") | F47: =IFERROR(SUM(E47*D47),"") | G47: =IF(D47="","",$F$11+8)
C48: =IFERROR(VLOOKUP(B48,Preço!B:C,2,0),"") | E48: =IFERROR(VLOOKUP(B48,Preço!B:D,3,0),"") | F48: =IFERROR(SUM(E48*D48),"") | G48: =IF(D48="","",$F$11+8)
... C70: =IFERROR(VLOOKUP(B70,Preço!B:C,2,0),"") | E70: =IFERROR(VLOOKUP(B70,Preço!B:D,3,0),"") | F70: =IFERROR(SUM(E70*D70),"") | G70: =IF(D70="","",$F$11+8)
B71: Observações da Nota Fiscal: | E71: Total: | F71: =SUM(F20:F70) -> 42789.03
E72: Frete | F72: =IF(J11<=5,"3,5%", IF(J11<=10,"5,0%", IF(J11<=15,"7,0%", IF(J11<=31,"10%", "Fora do intervalo")))) -> 10%
E73: Total Pedido: | F73: =(F71*F72)+F71 -> 47067.933
E74: Cond. Pgto.: | F74: =IF(F71=0,"",IF(F71<=5000,"7 dias", IF(F71<=10000,"30 dias", IF(F71<=20000,"30/60 dias", "30/60/90 dias")))) -> 30/60/90 dias
E75: =IF(F73=0,"",IF(F73<2500,"FATURAMENTO MÍNIMO: R$ 2.500,00",""))

Sheet Cliente
A1: Razao Social | B1: CNPJ/CPF | C1: Insc. Estadual | D1: Endereço: | E1: CEP | F1: Endereço Entrega: | G1: CEP Entrega
A2: SINTESE BIOTECNOLOGIA LTDA | B2: 13.545.241/0001-68 | C2: 0017632680098 | D2: Avenida Del Rey, 111, Belo Horizonte - 30775-240 (MG) | E2: 30775-240 | F2: Avenida Del Rey, 111, Belo Horizonte - 30775-240 (MG) | G2: 30775-240

Sheet Preço
A1: Nome: | B1: Código | C1: Produto | D1: Valor Unitário
A2: SINTESE BIOTECNOLOGIA LTDA | B2: 59021 | C2: ANTISSORO MONOVALENTE SALMONELLA O:4,5 | D2: 267.94
A3: SINTESE BIOTECNOLOGIA LTDA | B3: 59062 | C3: ANTISSORO MONOVALENTE SALMONELLA O:6, 7, 8 | D3: 465.98
A4: SINTESE BIOTECNOLOGIA LTDA | B4: 59081 | C4: ANTISSORO MONOVALENTE SALMONELLA O:7 | D4: 291.25
A5: SINTESE BIOTECNOLOGIA LTDA | B5: 59091 | C5: ANTISSORO MONOVALENTE SALMONELLA O:8 | D5: 291.25
A6: SINTESE BIOTECNOLOGIA LTDA | B6: 59101 | C6: ANTISSORO MONOVALENTE SALMONELLA O:9 | D6: 291.25
A7: SINTESE BIOTECNOLOGIA LTDA | B7: 59112 | C7: ANTISSORO MONOVALENTE SALMONELLA O:3, 10, 15 | D7: 535.89
A8: SINTESE BIOTECNOLOGIA LTDA | B8: 59131 | C8: ANTISSORO MONOVALENTE SALMONELLA O:1, 3, 19 | D8: 617.51
A9: SINTESE BIOTECNOLOGIA LTDA | B9: 59141 | C9: ANTISSORO MONOVALENTE SALMONELLA O:11 | D9: 695.4
A10: SINTESE BIOTECNOLOGIA LTDA | B10: 59162 | C10: ANTISSORO MONOVALENTE SALMONELLA O:13, 22, 23 | D10: 698.98
A11: SINTESE BIOTECNOLOGIA LTDA | B11: 60121 | C11: ANTISSORO MONOVALENTE SALMONELLA H:B | D11: 291.25
A12: SINTESE BIOTECNOLOGIA LTDA | B12: 60131 | C12: ANTISSORO MONOVALENTE SALMONELLA H:C | D12: 156.59
A13: SINTESE BIOTECNOLOGIA LTDA | B13: 60141 | C13: ANTISSORO MONOVALENTE SALMONELLA H:D | D13: 291.49
... A12085: SINTESE BIOTECNOLOGIA LTDA | B12085: 1713040122 | C12085: FATORES DE LISE CELULAR 10X96 | D12085: 1493.58
A12086: SINTESE BIOTECNOLOGIA LTDA | B12086: 0016-0104 | C12086: ANTICORPO SHEEP ANTI ACETAMINOPHEN 0.5 ml Sheep | D12086: 3066.66
A12087: SINTESE BIOTECNOLOGIA LTDA | B12087: 0030-2004 | C12087: ANTICORPO RABBIT ANTI ACETYLCHOLINE 1 ml Rabbit | D12087: 3066.66
A12088: SINTESE BIOTECNOLOGIA LTDA | B12088: 0100-0023 | C12088: ANTICORPO RABBIT ANTI 4-FLUORO-7-NITROBENZOFURAZAN 1 ml Rabbit | D12088: 2360.02
A12089: SINTESE BIOTECNOLOGIA LTDA | B12089: 0100-0025 | C12089: ANTICORPO SYNTHETIC S-ADENOSYL-HOMOCYSTEINE 5 mg | D12089: 1065.58
A12090: SINTESE BIOTECNOLOGIA LTDA | B12090: 0100-0026 | C12090: ANTICORPO RABBIT ANTI S-ADENOSYL-HOMOCYSTEINE 1 ml Rabbit | D12090: 2404.18
A12091: SINTESE BIOTECNOLOGIA LTDA | B12091: 0100-0035 | C12091: ANTICORPO NATIVE LIPOTEICHOIC ACID 1 mg | D12091: 1290.42
A12092: SINTESE BIOTECNOLOGIA LTDA | B12092: 0100-0075 | C12092: ANTICORPO RAT ANTI HUMAN DOPAMINE TRANSPORTER DAT-Nt(4F8) 0.1 ml Rat | D12092: 6337.28
A12093: SINTESE BIOTECNOLOGIA LTDA | B12093: 0100-0076 | C12093: ANTICORPO MOUSE ANTI BOVINE DYNEIN CYTOPLASMIC 74kDa 74.1 0.1 mg Mouse | D12093: 5453.17
A12094: SINTESE BIOTECNOLOGIA LTDA | B12094: 0100-0119 | C12094: ANTICORPO MOUSE ANTI THYROXINE T4:1-28.1 (BGN/098/281) 1 mg Mouse | D12094: 5943
A12095: SINTESE BIOTECNOLOGIA LTDA | B12095: 0100-0153 | C12095: ANTICORPO RABBIT ANTI CLOSTRIDIUM DIFFICILE TOXIN A 1 ml Rabbit | D12095: 2385.71
A12096: SINTESE BIOTECNOLOGIA LTDA | B12096: 0100-0173 | C12096: ANTICORPO RABBIT ANTI STREPTOKINASE 1 ml Rabbit | D12096: 3066.66
A12097: SINTESE BIOTECNOLOGIA LTDA | B12097: 0100-0220 | C12097: ANTICORPO MOUSE ANTI HUMAN CD140a 35248 (57/20) 0.1 mg Mouse | D12097: 2385.71
... A19683: SINTESE BIOTECNOLOGIA LTDA | B19683: VPA00854 | C19683: Anticorpo colageno VII | D19683: 4370.73

Sheet Planilha1
A1: cod_empresa | B1: num_list_preco | C1: cod_cliente | D1: nom_cliente | E1: cod_item | F1: den_item | G1: pre_unit
A2: 15 | B2: 331 | E2: 144 | F2: LIQUICHEK HEMATOLOGY 16T CONTROL 12 X 2 5 ML | G2: 3500
A3: 15 | B3: 331 | E3: 146 | F3: CONTROLE LIQUICHEK M CARDIACOS PLUS LT NIVEL 1 | G3: 788
A4: 15 | B4: 331 | E4: 147 | F4: CONTROLE LIQUICHEK M CARDIACOS PLUS LT NIVEL 2 | G4: 788
A5: 15 | B5: 331 | E5: 148 | F5: CONTROLE LIQUICHEK M CARDIACOS PLUS LT NIVEL 3 | G5: 788
A6: 15 | B6: 331 | E6: 149 | F6: LIQUICHECK CARDIAC MARKERS PLUS CONTROL LT NIVEL BAIXO | G6: 788
A7: 15 | B7: 331 | E7: 180 | F7: CONTROLE LIQUICHEK MARCADOR CARDIACO PLUS TRINIVEL | G7: 788
A8: 15 | B8: 331 | E8: 181 | F8: CONTROLE LIQUICHEK MARCADORES CARDIACOS PLUS NIVEL 1 | G8: 901
A9: 15 | B9: 331 | E9: 182 | F9: CONTROLE LIQUICHEK MARCADORES CARDIACOS PLUS NIVEL 2 | G9: 901
A10: 15 | B10: 331 | E10: 183 | F10: CONTROLE LIQUICHEK MARCADORES CARDIACOS PLUS NIVEL 3 | G10: 901
A11: 15 | B11: 331 | E11: 195 | F11: Controle Liquichek Quimica Urina - Nivel 1 | G11: 1636
A12: 15 | B12: 331 | E12: 196 | F12: Controle Liquichek Quimica Urina - Nivel 2 | G12: 1636
A13: 15 | B13: 331 | E13: 227 | F13: CONTROLE LIQUICHEK TORCH PLUS POSITIVO ENSAIADO | G13: 3373
... A429: 15 | B429: 331 | E429: 91766 | F429: SOLUC?O DE LIMPEZA - DECON 90 (1X5L) | G429: 1801.55
A430: 05 | B430: 732 | E430: 92461 | F430: GNUS - SOFTWARE DO LEITOR GEENIUS | G430: 363.55
A431: 15 | B431: 331 | E431: 92465 | F431: LEITOR GEENIUS | G431: 62483
A432: 15 | B432: 331 | E432: 92482 | F432: GNUS - FERRAMENTA DE CALIBRAC?O DE FORMA | G432: 6104.81
A433: 15 | B433: 331 | E433: 92501 | F433: Geenius Supplemental Assay, 20 Tests | G433: 3224
A434: 15 | B434: 331 | E434: 92502 | F434: Controle Geenius HCV | G434: 764
A435: 15 | B435: 331 | E435: 93025 | F435: IQ-PREP - PONTEIRA DE PIPETAGEM 1000UL (OBSOLETO - USAR 12014446) | G435: 37368.69
A436: 15 | B436: 331 | E436: 93030 | F436: IQ-PREP - O-RING CENTRAL | G436: 1322.44
A437: 15 | B437: 331 | E437: 93137 | F437: EVOLIS - BOMBA DE DILUIC?O | G437: 10240.25
A438: 15 | B438: 331 | E438: 93138 | F438: EVOLIS - VALVULA DA BOMBA DE INJEC?O VP9101 | G438: 2009.89
A439: 15 | B439: 331 | E439: 93344 | F439: EVOLIS - MEMBRANA DA BOMBA DE VACUO | G439: 5429.9
A440: 15 | B440: 331 | E440: 93354 | F440: IQ-PREP - FIXADOR DE ROSCA | G440: 1589.46
A441: 15 | B441: 331 | E441: 93389 | F441: EVOLIS - FERRAMENTA DE ALINHAMENTO DE RACK | G441: 10602.3
A442: 15 | B442: 331 | E442: 93401 | F442: CABO USB PARA NOTEBOOK ADAGIO | G442: 19.37
... A13066: 15 | B13066: 331 | E13066: 12006479 | F13066: IH1000 - GUIA DO EIXO Y DO BRACO DE TRANSPORTE | G13066: 7918.68
A13067: 05 | B13067: 732 | E13067: 12006574 | F13067: Kit PCR em Tempo Real iQ Check Vibrio | G13067: 12782
A13068: 15 | B13068: 331 | E13068: 12006823 | F13068: Agua livre de DNA para Legionella | G13068: 481.8
A13069: 15 | B13069: 331 | E13069: 12006834 | F13069: QX200 - SUPORTE DA PLACA | G13069: 4549.73
A13070: 15 | B13070: 331 | E13070: 12006848 | F13070: D-100 HEMOGLOBINA | G13070: 824709
A13071: 15 | B13071: 331 | E13071: 12006893 | F13071: VNBS - ATUALIZAC?O DA LAVAGEM DO SISTEMA DE INJEC?O | G13071: 21511.87
A13072: 15 | B13072: 331 | E13072: 12007020 | F13072: COLUNA FORESIGHT NUVIA HP-Q, 1 ML | G13072: 3840.1
A13073: 15 | B13073: 331 | E13073: 12007029 | F13073: Controle qUAntify Advance, Minipak (2 x 12 ml) | G13073: 324
A13074: 15 | B13074: 331 | E13074: 12007283 | F13074: BIO PLEX PRO PAINEL DE TRIAGEM DE CITOCINAS HUMANAS 48 PLEX | G13074: 33839.3
A13075: 15 | B13075: 331 | E13075: 12007305 | F13075: Agar RAPID Bacilus cereus, base desidratada, 500g | G13075: 1617
A13076: 15 | B13076: 331 | E13076: 12007306 | F13076: Suplemento 1 para Agar RAPIDB.cereus, suficiente para 10x500 ml | G13076: 1318.9
A13077: 15 | B13077: 331 | E13077: 12007307 | F13077: Suplemento 2 para Agar RAPIDB.cereus, suficiente para 10x500 ml | G13077: 1545.5
A13078: 15 | B13078: 331 | E13078: 12007385 | F13078: TRNSBLT - CONJUNTO DE ELETRODOS DE CONTATO | G13078: 2040.96
A13079: 15 | B13079: 331 | E13079: 12007392 | F13079: COLUNA FORESIGHT NUVIA APRIME 4A, 1 ML | G13079: 3805.52
... A13084: 15 | B13084: 331 | E13084: 12007602 | F13084: COMPUTADOR PARA GERENCIAMENTO DE EQUIPAMENTOS IHD | G13084: 50866.2
A13085: 05 | B13085: 732 | E13085: 12007729 | F13085: Impressora HP 2630 para uso com o sistema Evolis | G13085: 1603.64
A13086: 15 | B13086: 331 | E13086: 12007917 | F13086: CFX ALL - SOFTWARE GERENCIAMENTO Dx | G13086: 1715.9
A13087: 15 | B13087: 331 | E13087: 12007919 | F13087: Padr?o para painel de screening Bio-Plex Pro citocina humana, 96 ensaios | G13087: 863.5
A13088: 15 | B13088: 331 | E13088: 12007920 | F13088: Padr?o Painel de Triag Citocina Humana Bio-Plex Pro, 50x96 ensaios | G13088: 20958.3
A13089: 15 | B13089: 331 | E13089: 12007975 | F13089: Painel Imunoterapia Bio-Plex Pro Human, 20 plex, 1x96 pocos | G13089: 29910.1
A13090: 15 | B13090: 331 | E13090: 12008041 | F13090: Suplemento Seletivo Liofilizado RAPID E.coli 2 | G13090: 328.9
A13091: 15 | B13091: 331 | E13091: 12008202 | F13091: DDPCR EXPERT DESIGN ASSAY 200R | G13091: 8966.45
A13092: 15 | B13092: 331 | E13092: 12008256 | F13092: InteliQ Controle Multiqual Ensaiado, nivel 1 | G13092: 2483
A13093: 15 | B13093: 331 | E13093: 12008257 | F13093: InteliQ Controle Ensaiado Multiqual, nivel 2 | G13093: 2483
A13094: 15 | B13094: 331 | E13094: 12008258 | F13094: InteliQ Controle Ensaiado Multiqual, nivel 3 | G13094: 2483
A13095: 15 | B13095: 331 | E13095: 12008259 | F13095: InteliQ Controle Ensaiado Multiqual, Minipak, 3 x 3ml | G13095: 887
A13096: 15 | B13096: 331 | E13096: 12008276 | F13096: Controle InteliQ Imunoensaio especializado, nivel LTA, 6 x 4 ml | G13096: 2808
A13097: 15 | B13097: 331 | E13097: 12008277 | F13097: Controle InteliQ Imunoensaio especializado, nivel 1, 6 x 4 ml | G13097: 2087
... A13159: 15 | B13159: 331 | E13159: 12010184 | F13159: IH1000 - ENGRENAGEM DO EIXO Z DO PIPETADOR | G13159: 2927.16
A13160: 05 | B13160: 732 | E13160: 12010220 | F13160: Reliance One-Step Multiplex Supermix, 1,000 x 20 ?l reac?es, 5 ml | G13160: 13665.3
A13161: 15 | B13161: 331 | E13161: 12010221 | F13161: Supermix Reliance One-Step Multiplex, 2000 reac?es x 20uL, 10 mL | G13161: 26350.5
A13162: 15 | B13162: 331 | E13162: 12010405 | F13162: D10 Sistema Analisador de Hemoglobinas (DM) | G13162: 236665
A13163: 15 | B13163: 331 | E13163: 12010508 | F13163: VII-ALL - CD-ROM COM IMAGEM DA VERS?O CDM 5.4 WINDOWS 10 | G13163: 981.04
A13164: 15 | B13164: 331 | E13164: 12010522 | F13164: Tubulac?o do kit externo do carrinho de descarte de residuos ZE5 | G13164: 9802.28
A13165: 15 | B13165: 331 | E13165: 12010523 | F13165: Tampa do gal?o do kit externo de agua deionizada ZE5 | G13165: 4760.82
A13166: 15 | B13166: 331 | E13166: 12010701 | F13166: IH1000 - NOVO MODULO PDS COMPLETO V1.0 (SERVE NO IH-500) | G13166: 42965.22
A13167: 05 | B13167: 732 | E13167: 12010766 | F13167: IHD-PC FLEXPRO | G13167: 46348.06
A13168: 05 | B13168: 732 | E13168: 12010820 | F13168: IQ-PREP - RACK DE TUBO DE AMOSTRA 4 X 24 | G13168: 7286.83
A13169: 15 | B13169: 331 | E13169: 12010828 | F13169: Bio-Plex Pro Painel para detecc?o de citocinas de Camundongo Th17, 10 plex | G13169: 19537.1
A13170: 15 | B13170: 331 | E13170: 12010831 | F13170: IQ-PREP - BASE DE TRANSPORTE DAS RACKS DE TUBO DE AMOSTRA | G13170: 5399.37
A13171: 15 | B13171: 331 | E13171: 12010832 | F13171: IQ-PREP - RACK DE TUBO DE AMOSTRA 3 X 32 | G13171: 6575.92
A13172: 15 | B13172: 331 | E13172: 12010936 | F13172: GENE PLSR - PLACA ELETRONICA CONTROLADORA DA UNIDADE PRINCIPAL | G13172: 4056.34
A13173: 15 | B13173: 331 | E13173: 12010938 | F13173: GENE PLSR - CONJUNTO DO VISOR | G13173: 2275.34
A13174: 15 | B13174: 331 | E13174: 12010947 | F13174: TAMP?O DE BLOQUEIO EVERYBLOT, 50 ML | G13174: 344.86
A13175: 15 | B13175: 331 | E13175: 12011319 | F13175: CFX Opus 96 | G13175: 160505.18
A13176: 15 | B13176: 331 | E13176: 12011334 | F13176: Controle Liquichek Diabetes Trilevel Minipak, 3 x 1 mL | G13176: 1165
A13177: 15 | B13177: 331 | E13177: 12011363 | F13177: VII-ALL - SOFTWARE ARCHIVE VIEWER 1.5 PARA WINDOWS 10 | G13177: 90.21
A13178: 15 | B13178: 331 | E13178: 12011375 | F13178: D10 - LINCENCA WINDOWS 10 | G13178: 308.05
A13179: 15 | B13179: 331 | E13179: 12011384 | F13179: D10 - KIT DE INSTALAC?O DA IMPRESSORA V2 | G13179: 7682.95
A13180: 15 | B13180: 331 | E13180: 12011452 | F13180: Sistema de PCR em Tempo Real CFX Opus 384 | G13180: 164112.35
... A13183: 15 | B13183: 331 | E13183: 12011936 | F13183: IH500 - ANEL DE VEDAC?O DO CONECTOR MACHO DO GAL?O DE ESGOTO | G13183: 1614.1
A13184: 05 | B13184: 732 | E13184: 12012009 | F13184: CFX OPUS - MODULO DE MOVIMENTAC?O DO DETECTOR DE 96 POCOS | G13184: 1217.25
A13185: 15 | B13185: 331 | E13185: 12012010 | F13185: CFX OPUS - MODULO DE MOVIMENTAC?O DO DETECTOR DE 384 POCOS | G13185: 1871.98
A13186: 15 | B13186: 331 | E13186: 12012096 | F13186: Esferas de purificac?o SEQuoia | G13186: 40018
A13187: 15 | B13187: 331 | E13187: 12012109 | F13187: GEL GO - LAMPADAS 302 NM | G13187: 1838.31
A13188: 15 | B13188: 331 | E13188: 12012147 | F13188: GEL GO - PROCEDIMENTO IQ/OQ | G13188: 667.63
A13189: 15 | B13189: 331 | E13189: 12012160 | F13189: BANDEJA AZUL PARA O SISTEMA DE IMAGEM GELDOC GO | G13189: 8150.12
A13190: 15 | B13190: 331 | E13190: 12012161 | F13190: Software Image Lab, USB, Edic?o de Seguranca, 5 licencas | G13190: 64446.6
A13191: 15 | B13191: 331 | E13191: 12012162 | F13191: SOFTWARE IMAGE LAB, EDIC?O DE SEGURANCA, 1 LICENCA | G13191: 13461.59
A13192: 15 | B13192: 331 | E13192: 12012164 | F13192: PROTETOR DE SEGURANCA UV PARA O SISTEMA DE IMAGEM GELDOC GO | G13192: 4666.34
A13193: 15 | B13193: 331 | E13193: 12012165 | F13193: BANDEJA BRANCA PARA O SISTEMA DE IMAGEM GELDOC GO | G13193: 5652.88
A13194: 15 | B13194: 331 | E13194: 12012171 | F13194: Ditiotreitol (DTT), 2mL | G13194: 761.2
A13195: 15 | B13195: 331 | E13195: 12012172 | F13195: Software QX Manager edicao regulatoria | G13195: 17631.57
A13196: 15 | B13196: 331 | E13196: 12012189 | F13196: BANDEJA UV/STAIN-FREE PARA O SISTEMA DE IMAGEM GELDOC GO | G13196: 5970.36
... A13252: 15 | B13252: 331 | E13252: 12013256 | F13252: IH1000 - KIT DE SUBSTITUIC?O DA BOMBA PERISTALTICA | G13252: 24518.15
A13253: 05 | B13253: 732 | E13253: 12013259 | F13253: Agua peptonada tamponada (BPW), pct 5l x 2 sacos | G13253: 260.7
A13254: 15 | B13254: 331 | E13254: 12013322 | F13254: Suplemento PIF, pcte com 1un, frasco de 2g | G13254: 240.9
A13255: 15 | B13255: 331 | E13255: 12013328 | F13255: Leitora de Gotas PCR Digital QX600 | G13255: 841500
A13256: 15 | B13256: 331 | E13256: 12013437 | F13256: IH500 - CABO DE ATERRAMENTO ELETRICO | G13256: 1014.9
A13257: 05 | B13257: 732 | E13257: 12013645 | F13257: D100 - MEMBRANA DL INLINE FILTER V4 | G13257: 642.23
A13258: 15 | B13258: 331 | E13258: 12013664 | F13258: D100 - CONJUNTO COMPLETO INLINE FILTER V4 | G13258: 2532.14
A13259: 15 | B13259: 331 | E13259: 12013714 | F13259: VNBS - DVD COM IMAGEM DO SOFTWARE GDM 3.3 | G13259: 287.66
A13260: 15 | B13260: 331 | E13260: 12013715 | F13260: VII-ALL - IMAGEM CDM 5.4 EM DVD PARA COMPUTADORES FLEXPRO | G13260: 281.43
...
